deform_conv2d_onnx_exporter.py
deform_conv2d_onnx_exporter-1.2.0.dist-info/METADATA
deform_conv2d_onnx_exporter-1.2.0.dist-info/WHEEL
deform_conv2d_onnx_exporter-1.2.0.dist-info/top_level.txt
deform_conv2d_onnx_exporter-1.2.0.dist-info/zip-safe
deform_conv2d_onnx_exporter-1.2.0.dist-info/RECORD
