Metadata-Version: 2.1
Name: deform-conv2d-onnx-exporter
Version: 1.2.0
Summary: A library to support onnx export of deform_conv2d in PyTorch.
Home-page: https://github.com/masamitsu-murase/deform_conv2d_onnx_exporter
Author: Masamitsu MURASE
Author-email: masamitsu.murase@gmail.com
License: MIT
Project-URL: Bug Reports, https://github.com/masamitsu-murase/deform_conv2d_onnx_exporter/issues
Project-URL: Source, https://github.com/masamitsu-murase/deform_conv2d_onnx_exporter
Keywords: deform_conv2d PyTorch ONNX
Platform: UNKNOWN
Requires-Python: >=3.6.*, <4
Requires-Dist: torch (>=1.8.0)
Requires-Dist: torchvision (>=0.9.0)
Provides-Extra: package
Requires-Dist: twine ; extra == 'package'
Requires-Dist: wheel ; extra == 'package'
Provides-Extra: test
Requires-Dist: onnx ; extra == 'test'
Requires-Dist: onnxruntime ; extra == 'test'
